geotexxx/__init__.py
geotexxx/gefxml_reader.py
geotexxx-0.3.6.dist-info/licenses/LICENSE.txt
geotexxx-0.3.6.dist-info/METADATA
geotexxx-0.3.6.dist-info/WHEEL
geotexxx-0.3.6.dist-info/top_level.txt
geotexxx-0.3.6.dist-info/zip-safe
geotexxx-0.3.6.dist-info/RECORD
