Metadata-Version: 2.4
Name: geotexxx
Version: 0.3.6
Summary: Verwerken van geotechnisch grondonderzoek
Author-email: Thomas van der Linden <t.van.der.linden@amsterdam.nl>
License-Expression: EUPL-1.2
Project-URL: Homepage, https://github.com/ic144/geotexxx_package
Project-URL: Repository, https://github.com/ic144/geotexxx_package
Project-URL: Issues, https://github.com/ic144/geotexxx_package/issues
Classifier: Programming Language :: Python :: 3
Requires-Python: >=3.11
License-File: LICENSE.txt
Requires-Dist: numpy
Requires-Dist: pandas
Requires-Dist: pyproj
Requires-Dist: setuptools
Requires-Dist: setuptools_scm
Requires-Dist: matplotlib
Requires-Dist: requests
Dynamic: license-file
